{
  "legislative_session": "2026",
  "identifier": "HB 279",
  "title": "Luggage for Children Placed in Out-of-home Care",
  "from_organization": "~{\"classification\": \"lower\"}",
  "classification": [
    "bill"
  ],
  "subject": [],
  "abstracts": [
    {
      "note": "summary",
      "abstract": "Luggage for Children Placed in Out-of-home Care;  Requires DCF to provide certain children with piece of luggage for certain purposes; provides department requirements; requires department to submit specified annual report to Legislature; provides sources of funding for distribution of pieces of luggage; requires department's direct-support organization to receive & use certain funding to administer law."
    }
  ],
  "other_titles": [],
  "other_identifiers": [],
  "actions": [
    {
      "description": "Filed",
      "date": "2025-10-28",
      "organization_id": "~{\"classification\": \"lower\"}",
      "classification": [
        "filing"
      ],
      "related_entities": [],
      "_processing": {
        "log_file_created": "2025-10-29T00:38:18Z"
      }
    }
  ],
  "sponsorships": [
    {
      "name": "Bartleman",
      "classification": "primary",
      "entity_type": "person",
      "primary": true,
      "person_id": "~{\"name\": \"Bartleman\"}",
      "organization_id": null
    }
  ],
  "related_bills": [],
  "versions": [
    {
      "note": "H 279 Filed",
      "links": [
        {
          "url": "https://flsenate.gov/Session/Bill/2026/279/BillText/Filed/PDF",
          "media_type": "application/pdf"
        }
      ],
      "date": "",
      "classification": ""
    }
  ],
  "documents": [],
  "citations": [
    {
      "publication": "Florida Statues",
      "citation": "39.401",
      "citation_type": "proposed",
      "effective": null,
      "expires": null,
      "url": "https://flsenate.gov/laws/statutes/2025/39.401"
    }
  ],
  "sources": [
    {
      "url": "https://flsenate.gov/Session/Bill/2026/279/ByCategory",
      "note": ""
    }
  ],
  "extras": {},
  "jurisdiction": {
    "id": "ocd-jurisdiction/country:us/state:fl/government",
    "name": "Florida",
    "classification": "state",
    "division_id": "ocd-division/country:us/state:fl"
  },
  "_processing": {
    "logs_latest_update": "2025-10-29T00:38:18Z"
  }
}