{
  "legislative_session": "2026",
  "identifier": "SB 108",
  "title": "Resolution of Disputed Property Insurance Claims",
  "from_organization": "~{\"classification\": \"upper\"}",
  "classification": [
    "bill"
  ],
  "subject": [
    "appropriations",
    "insurance"
  ],
  "abstracts": [
    {
      "note": "summary",
      "abstract": "Resolution of Disputed Property Insurance Claims;  Requiring, rather than authorizing, parties in a property insurance claim dispute to participate in mediation; providing that mediation is a condition precedent to commencing litigation; requiring all insureds, or their representatives, to attend the mediation; requiring the policyholder to provide the insurer with any information and certain documents within a specified timeframe after mediation is invoked; revising the definition of the term \u201cclaim\u201d, etc.\r\n    \r\n        APPROPRIATION:\r\n        $1,000,000"
    }
  ],
  "other_titles": [],
  "other_identifiers": [],
  "actions": [
    {
      "description": "Filed",
      "date": "2025-10-07",
      "organization_id": "~{\"classification\": \"upper\"}",
      "classification": [
        "filing"
      ],
      "related_entities": [],
      "_processing": {
        "log_file_created": "2025-10-23T19:01:22Z"
      }
    },
    {
      "description": "Referred to Banking and Insurance; Appropriations Committee on Agriculture, Environment, and General Government; Fiscal Policy",
      "date": "2025-10-13",
      "organization_id": "~{\"classification\": \"upper\"}",
      "classification": [
        "referral-committee"
      ],
      "related_entities": [],
      "_processing": {
        "log_file_created": "2025-10-23T19:01:22Z"
      }
    }
  ],
  "sponsorships": [
    {
      "name": "Polsky",
      "classification": "primary",
      "entity_type": "person",
      "primary": true,
      "person_id": "~{\"name\": \"Polsky\"}",
      "organization_id": null
    }
  ],
  "related_bills": [],
  "versions": [
    {
      "note": "S 108 Filed",
      "links": [
        {
          "url": "https://flsenate.gov/Session/Bill/2026/108/BillText/Filed/HTML",
          "media_type": "text/html"
        },
        {
          "url": "https://flsenate.gov/Session/Bill/2026/108/BillText/Filed/PDF",
          "media_type": "application/pdf"
        }
      ],
      "date": "",
      "classification": ""
    }
  ],
  "documents": [],
  "citations": [
    {
      "publication": "Florida Statues",
      "citation": "627.7015",
      "citation_type": "proposed",
      "effective": null,
      "expires": null,
      "url": "https://flsenate.gov/laws/statutes/2025/627.7015"
    },
    {
      "publication": "Florida Statues",
      "citation": "627.7074",
      "citation_type": "proposed",
      "effective": null,
      "expires": null,
      "url": "https://flsenate.gov/laws/statutes/2025/627.7074"
    }
  ],
  "sources": [
    {
      "url": "https://flsenate.gov/Session/Bill/2026/108/ByCategory",
      "note": ""
    }
  ],
  "extras": {},
  "jurisdiction": {
    "id": "ocd-jurisdiction/country:us/state:fl/government",
    "name": "Florida",
    "classification": "state",
    "division_id": "ocd-division/country:us/state:fl"
  },
  "_processing": {
    "logs_latest_update": "2025-10-23T19:01:22Z"
  }
}