{
  "legislative_session": "2026",
  "identifier": "SB 134",
  "title": "Telephone Solicitation",
  "from_organization": "~{\"classification\": \"upper\"}",
  "classification": [
    "bill"
  ],
  "subject": [
    "and solicitations"
  ],
  "abstracts": [
    {
      "note": "summary",
      "abstract": "Telephone Solicitation;  Revising the definition of the terms \u201ctelephone solicitor\u201d and \u201ctelephonic sales call\u201d; revising the conditions for awarding attorney fees in civil actions relating to telephone solicitation, etc."
    }
  ],
  "other_titles": [],
  "other_identifiers": [],
  "actions": [
    {
      "description": "Filed",
      "date": "2025-10-08",
      "organization_id": "~{\"classification\": \"upper\"}",
      "classification": [
        "filing"
      ],
      "related_entities": [],
      "_processing": {
        "log_file_created": "2025-10-23T19:01:22Z"
      }
    },
    {
      "description": "Referred to Commerce and Tourism; Judiciary; Rules",
      "date": "2025-10-21",
      "organization_id": "~{\"classification\": \"upper\"}",
      "classification": [
        "referral-committee"
      ],
      "related_entities": [],
      "_processing": {
        "log_file_created": "2025-10-23T19:01:22Z"
      }
    }
  ],
  "sponsorships": [
    {
      "name": "Polsky",
      "classification": "primary",
      "entity_type": "person",
      "primary": true,
      "person_id": "~{\"name\": \"Polsky\"}",
      "organization_id": null
    }
  ],
  "related_bills": [],
  "versions": [
    {
      "note": "S 134 Filed",
      "links": [
        {
          "url": "https://flsenate.gov/Session/Bill/2026/134/BillText/Filed/HTML",
          "media_type": "text/html"
        },
        {
          "url": "https://flsenate.gov/Session/Bill/2026/134/BillText/Filed/PDF",
          "media_type": "application/pdf"
        }
      ],
      "date": "",
      "classification": ""
    }
  ],
  "documents": [],
  "citations": [
    {
      "publication": "Florida Statues",
      "citation": "501.059",
      "citation_type": "proposed",
      "effective": null,
      "expires": null,
      "url": "https://flsenate.gov/laws/statutes/2025/501.059"
    },
    {
      "publication": "Florida Statues",
      "citation": "517.0615",
      "citation_type": "proposed",
      "effective": null,
      "expires": null,
      "url": "https://flsenate.gov/laws/statutes/2025/517.0615"
    }
  ],
  "sources": [
    {
      "url": "https://flsenate.gov/Session/Bill/2026/134/ByCategory",
      "note": ""
    }
  ],
  "extras": {},
  "jurisdiction": {
    "id": "ocd-jurisdiction/country:us/state:fl/government",
    "name": "Florida",
    "classification": "state",
    "division_id": "ocd-division/country:us/state:fl"
  },
  "_processing": {
    "logs_latest_update": "2025-10-23T19:01:22Z",
    "text_extraction_latest_update": "2025-10-23T19:16:08.064783Z"
  }
}