{
  "legislative_session": "2026",
  "identifier": "HB 77",
  "title": "Public Postsecondary Safety Policies and Procedures",
  "from_organization": "~{\"classification\": \"lower\"}",
  "classification": [
    "bill"
  ],
  "subject": [
    "k"
  ],
  "abstracts": [
    {
      "note": "summary",
      "abstract": "Public Postsecondary Safety Policies and Procedures;  Requires state universities & FCS institutions to adopt & implement specified policies & procedures relating to safety; provides requirements for policies & procedures; & requires annual review & updates policies & procedures."
    }
  ],
  "other_titles": [],
  "other_identifiers": [],
  "actions": [
    {
      "description": "Filed",
      "date": "2025-10-02",
      "organization_id": "~{\"classification\": \"lower\"}",
      "classification": [
        "filing"
      ],
      "related_entities": [],
      "_processing": {
        "log_file_created": "2025-10-23T19:01:22Z"
      }
    },
    {
      "description": "Referred to Education Administration Subcommittee",
      "date": "2025-10-07",
      "organization_id": "~{\"classification\": \"lower\"}",
      "classification": [
        "referral-committee"
      ],
      "related_entities": [],
      "_processing": {
        "log_file_created": "2025-10-23T19:01:22Z"
      }
    },
    {
      "description": "Referred to Education & Employment Committee",
      "date": "2025-10-07",
      "organization_id": "~{\"classification\": \"lower\"}",
      "classification": [
        "referral-committee"
      ],
      "related_entities": [],
      "_processing": {
        "log_file_created": "2025-10-23T19:01:22Z"
      }
    },
    {
      "description": "Now in Education Administration Subcommittee",
      "date": "2025-10-07",
      "organization_id": "~{\"classification\": \"lower\"}",
      "classification": [],
      "related_entities": [],
      "_processing": {
        "log_file_created": "2025-10-23T19:01:22Z"
      }
    }
  ],
  "sponsorships": [
    {
      "name": "Woodson",
      "classification": "primary",
      "entity_type": "person",
      "primary": true,
      "person_id": "~{\"name\": \"Woodson\"}",
      "organization_id": null
    }
  ],
  "related_bills": [],
  "versions": [
    {
      "note": "H 77 Filed",
      "links": [
        {
          "url": "https://flsenate.gov/Session/Bill/2026/77/BillText/Filed/PDF",
          "media_type": "application/pdf"
        }
      ],
      "date": "",
      "classification": ""
    }
  ],
  "documents": [],
  "citations": [],
  "sources": [
    {
      "url": "https://flsenate.gov/Session/Bill/2026/77/ByCategory",
      "note": ""
    }
  ],
  "extras": {},
  "jurisdiction": {
    "id": "ocd-jurisdiction/country:us/state:fl/government",
    "name": "Florida",
    "classification": "state",
    "division_id": "ocd-division/country:us/state:fl"
  },
  "_processing": {
    "logs_latest_update": "2025-10-23T19:01:22Z"
  }
}